dbting/VERSION
dbting/__init__.py
dbting/batch_to_datalake.py
dbting/cli.py
dbting/external_tables.py
dbting/ingest.py
dbting/qm.py
dbting/utils.py
dbting/xlsx_to_json_mapping.py
dbting/templates/__init__.py
dbting/templates/create_batch_table.sql
dbting/templates/create_datalake_table.sql
dbting/templates/drop_batch_table.sql
dbting/templates/drop_datalake_table.sql
dbting/templates/sql_batch_to_datalake.sql
dbt_ing-0.6.5.dist-info/LICENSE
dbt_ing-0.6.5.dist-info/METADATA
dbt_ing-0.6.5.dist-info/WHEEL
dbt_ing-0.6.5.dist-info/entry_points.txt
dbt_ing-0.6.5.dist-info/top_level.txt
dbt_ing-0.6.5.dist-info/zip-safe
dbt_ing-0.6.5.dist-info/RECORD
